{
    "display": {
        "icon": {
            "item": "minecraft:snow_block",
            "nbt": "{}"
        },
        "title": [
            [
                {
                    "text": "Snow Village",
                    "color": "white"
                },
                {
                    "text": ""
                }
            ]
        ],
        "frame": "task",
        "description": [
            {
                "text": "Travel across towns on the mountains!\n\n\u00a76Teddyishappyl",
                "color": "green"
            }
        ],
        "show_toast": false,
        "announce_to_chat": false,
        "hidden": false
    },
    "parent": "pr:plot_n2_n4",
    "criteria": {
        "tick": {
            "trigger": "minecraft:impossible"
        }
    }
}