{
	"textures": {
		"0": "kello:item/decal/melloflora_lantern_blue"
	},
	"elements": [
		{
			"from": [
				6.9340931866941204,
				14.150370767308583,
				7.4078295481634004
			],
			"to": [
				8.236868180734639,
				14.150370767308583,
				8.5921704518366
			],
			"rotation": {
				"angle": 22.5,
				"axis": "z",
				"origin": [
					8,
					14.150370767308583,
					8
				]
			},
			"faces": {
				"up": {
					"uv": [
						8,
						5.5,
						3.5,
						0
					],
					"rotation": 90,
					"texture": "#0",
					"tintindex": 0
				},
				"down": {
					"uv": [
						8,
						0,
						3.5,
						5.5
					],
					"rotation": 270,
					"texture": "#0",
					"tintindex": 0
				}
			}
		},
		{
			"from": [
				7.4078295481634004,
				14.150370767308583,
				6.9340931866941204
			],
			"to": [
				8.5921704518366,
				14.150370767308583,
				8.236868180734639
			],
			"rotation": {
				"angle": -22.5,
				"axis": "x",
				"origin": [
					8,
					14.150370767308583,
					8
				]
			},
			"faces": {
				"up": {
					"uv": [
						8,
						0,
						3.5,
						5.5
					],
					"texture": "#0",
					"tintindex": 0
				},
				"down": {
					"uv": [
						8,
						5.5,
						3.5,
						0
					],
					"texture": "#0",
					"tintindex": 0
				}
			}
		},
		{
			"from": [
				7.4078295481634004,
				14.150370767308583,
				7.76313181926536
			],
			"to": [
				8.5921704518366,
				14.150370767308583,
				9.06590681330588
			],
			"rotation": {
				"angle": 22.5,
				"axis": "x",
				"origin": [
					8,
					14.150370767308583,
					8
				]
			},
			"faces": {
				"up": {
					"uv": [
						8,
						5.5,
						3.5,
						0
					],
					"texture": "#0",
					"tintindex": 0
				},
				"down": {
					"uv": [
						8,
						0,
						3.5,
						5.5
					],
					"texture": "#0",
					"tintindex": 0
				}
			}
		},
		{
			"from": [
				7.76313181926536,
				14.150370767308583,
				7.4078295481634004
			],
			"to": [
				9.06590681330588,
				14.150370767308583,
				8.5921704518366
			],
			"rotation": {
				"angle": -22.5,
				"axis": "z",
				"origin": [
					8,
					14.150370767308583,
					8
				]
			},
			"faces": {
				"up": {
					"uv": [
						8,
						0,
						3.5,
						5.5
					],
					"rotation": 90,
					"texture": "#0",
					"tintindex": 0
				},
				"down": {
					"uv": [
						8,
						5.5,
						3.5,
						0
					],
					"rotation": 270,
					"texture": "#0",
					"tintindex": 0
				}
			}
		},
		{
			"from": [
				12.814095582557382,
				-9.849629232691417,
				7.4078295481634004
			],
			"to": [
				12.814095582557382,
				-8.546854238650898,
				8.5921704518366
			],
			"rotation": {
				"angle": -22.5,
				"axis": "z",
				"origin": [
					8.474923670645895,
					1.69196525981957,
					8
				]
			},
			"faces": {
				"north": {
					"uv": [
						0,
						0,
						0,
						0
					],
					"rotation": 270,
					"texture": "#0"
				},
				"east": {
					"uv": [
						16,
						10.5,
						11.5,
						16
					],
					"rotation": 180,
					"texture": "#0",
					"tintindex": 0
				},
				"south": {
					"uv": [
						0,
						0,
						0,
						0
					],
					"rotation": 90,
					"texture": "#0"
				},
				"west": {
					"uv": [
						16,
						16,
						11.5,
						10.5
					],
					"texture": "#0",
					"tintindex": 0
				}
			}
		},
		{
			"from": [
				3.185904417442619,
				-9.849629232691417,
				7.4078295481634004
			],
			"to": [
				3.185904417442619,
				-8.546854238650898,
				8.5921704518366
			],
			"rotation": {
				"angle": 22.5,
				"axis": "z",
				"origin": [
					7.525076329354105,
					1.69196525981957,
					8
				]
			},
			"faces": {
				"north": {
					"uv": [
						0,
						0,
						0,
						0
					],
					"rotation": 270,
					"texture": "#0"
				},
				"east": {
					"uv": [
						11.5,
						16,
						16,
						10.5
					],
					"texture": "#0",
					"tintindex": 0
				},
				"south": {
					"uv": [
						0,
						0,
						0,
						0
					],
					"rotation": 90,
					"texture": "#0"
				},
				"west": {
					"uv": [
						11.5,
						10.5,
						16,
						16
					],
					"rotation": 180,
					"texture": "#0",
					"tintindex": 0
				}
			}
		},
		{
			"from": [
				7.4078295481634004,
				-6.301439136985616,
				15.59031293134447
			],
			"to": [
				8.5921704518366,
				-5.711049648913939,
				15.59031293134447
			],
			"rotation": {
				"angle": 45,
				"axis": "x",
				"origin": [
					8,
					1.763203810416453,
					7.525076329354105
				]
			},
			"faces": {
				"north": {
					"uv": [
						11.5125,
						13.5,
						16,
						15.98625
					],
					"rotation": 180,
					"texture": "#0",
					"tintindex": 0
				},
				"east": {
					"uv": [
						0,
						0,
						0,
						0
					],
					"rotation": 270,
					"texture": "#0"
				},
				"south": {
					"uv": [
						11.5125,
						13.5,
						16,
						15.98625
					],
					"rotation": 180,
					"texture": "#0",
					"tintindex": 0
				},
				"west": {
					"uv": [
						0,
						0,
						0,
						0
					],
					"rotation": 90,
					"texture": "#0"
				}
			}
		},
		{
			"from": [
				7.4078295481634004,
				-6.301439136985616,
				0.4096870686555292
			],
			"to": [
				8.5921704518366,
				-5.711049648913939,
				0.4096870686555292
			],
			"rotation": {
				"angle": -45,
				"axis": "x",
				"origin": [
					8,
					1.763203810416453,
					8.474923670645895
				]
			},
			"faces": {
				"north": {
					"uv": [
						16,
						13.5,
						11.5125,
						15.98625
					],
					"rotation": 180,
					"texture": "#0",
					"tintindex": 0
				},
				"east": {
					"uv": [
						0,
						0,
						0,
						0
					],
					"rotation": 270,
					"texture": "#0"
				},
				"south": {
					"uv": [
						16,
						13.5,
						11.5125,
						15.98625
					],
					"rotation": 180,
					"texture": "#0",
					"tintindex": 0
				},
				"west": {
					"uv": [
						0,
						0,
						0,
						0
					],
					"rotation": 90,
					"texture": "#0"
				}
			}
		},
		{
			"from": [
				7.4078295481634004,
				-9.849629232691417,
				12.814095582557382
			],
			"to": [
				8.5921704518366,
				-8.546854238650898,
				12.814095582557382
			],
			"rotation": {
				"angle": 22.5,
				"axis": "x",
				"origin": [
					8,
					1.69196525981957,
					8.474923670645895
				]
			},
			"faces": {
				"north": {
					"uv": [
						11.5,
						16,
						16,
						10.5
					],
					"texture": "#0",
					"tintindex": 0
				},
				"east": {
					"uv": [
						0,
						0,
						0,
						0
					],
					"rotation": 90,
					"texture": "#0"
				},
				"south": {
					"uv": [
						11.5,
						10.5,
						16,
						16
					],
					"rotation": 180,
					"texture": "#0",
					"tintindex": 0
				},
				"west": {
					"uv": [
						0,
						0,
						0,
						0
					],
					"rotation": 270,
					"texture": "#0"
				}
			}
		},
		{
			"from": [
				7.4078295481634004,
				-9.849629232691417,
				3.185904417442619
			],
			"to": [
				8.5921704518366,
				-8.546854238650898,
				3.185904417442619
			],
			"rotation": {
				"angle": -22.5,
				"axis": "x",
				"origin": [
					8,
					1.69196525981957,
					7.525076329354105
				]
			},
			"faces": {
				"north": {
					"uv": [
						16,
						10.5,
						11.5,
						16
					],
					"rotation": 180,
					"texture": "#0",
					"tintindex": 0
				},
				"east": {
					"uv": [
						0,
						0,
						0,
						0
					],
					"rotation": 90,
					"texture": "#0"
				},
				"south": {
					"uv": [
						16,
						16,
						11.5,
						10.5
					],
					"texture": "#0",
					"tintindex": 0
				},
				"west": {
					"uv": [
						0,
						0,
						0,
						0
					],
					"rotation": 270,
					"texture": "#0"
				}
			}
		},
		{
			"from": [
				12.102303731176846,
				-8.308798748739644,
				7.289098630501926
			],
			"to": [
				13.642540560540311,
				-8.308798748739644,
				8.710901369498073
			],
			"rotation": {
				"angle": -22.5,
				"axis": "z",
				"origin": [
					8,
					2.166888930465464,
					8
				]
			},
			"faces": {
				"up": {
					"uv": [
						12.5,
						0,
						8,
						5.5
					],
					"rotation": 90,
					"texture": "#0",
					"tintindex": 0
				},
				"down": {
					"uv": [
						12.5,
						5.5,
						8,
						0
					],
					"rotation": 270,
					"texture": "#0",
					"tintindex": 0
				}
			}
		},
		{
			"from": [
				2.3574594394596877,
				-8.308798748739644,
				7.289098630501926
			],
			"to": [
				3.897696268823154,
				-8.308798748739644,
				8.710901369498073
			],
			"rotation": {
				"angle": 22.5,
				"axis": "z",
				"origin": [
					8,
					2.166888930465464,
					8
				]
			},
			"faces": {
				"up": {
					"uv": [
						12.5,
						5.5,
						8,
						0
					],
					"rotation": 90,
					"texture": "#0",
					"tintindex": 0
				},
				"down": {
					"uv": [
						12.5,
						0,
						8,
						5.5
					],
					"rotation": 270,
					"texture": "#0",
					"tintindex": 0
				}
			}
		},
		{
			"from": [
				7.289098630501926,
				-8.308798748739644,
				12.102303731176846
			],
			"to": [
				8.710901369498073,
				-8.308798748739644,
				13.642540560540311
			],
			"rotation": {
				"angle": 22.5,
				"axis": "x",
				"origin": [
					8,
					2.166888930465464,
					8
				]
			},
			"faces": {
				"up": {
					"uv": [
						12.5,
						5.5,
						8,
						0
					],
					"texture": "#0",
					"tintindex": 0
				},
				"down": {
					"uv": [
						12.5,
						0,
						8,
						5.5
					],
					"texture": "#0",
					"tintindex": 0
				}
			}
		},
		{
			"from": [
				7.289098630501926,
				-8.308798748739644,
				2.3574594394596877
			],
			"to": [
				8.710901369498073,
				-8.308798748739644,
				3.897696268823154
			],
			"rotation": {
				"angle": -22.5,
				"axis": "x",
				"origin": [
					8,
					2.166888930465464,
					8
				]
			},
			"faces": {
				"up": {
					"uv": [
						12.5,
						0,
						8,
						5.5
					],
					"texture": "#0",
					"tintindex": 0
				},
				"down": {
					"uv": [
						12.5,
						5.5,
						8,
						0
					],
					"texture": "#0",
					"tintindex": 0
				}
			}
		}
	],
	"display": {
		"head": {
			"rotation": [
				0,
				180,
				0
			]
		}
	}
}